PyTM/__init__.py
PyTM/__main__.py
PyTM/cli.py
PyTM/console.py
PyTM/settings.py
PyTM/commands/__init__.py
PyTM/commands/project.py
PyTM/commands/task.py
PyTM/core/__init__.py
PyTM/core/data_handler.py
PyTM/core/invoice_handler.py
PyTM/core/project_handler.py
PyTM/core/task_handler.py
python_pytm-0.0.15.dist-info/AUTHORS.rst
python_pytm-0.0.15.dist-info/LICENSE
python_pytm-0.0.15.dist-info/METADATA
python_pytm-0.0.15.dist-info/WHEEL
python_pytm-0.0.15.dist-info/entry_points.txt
python_pytm-0.0.15.dist-info/top_level.txt
python_pytm-0.0.15.dist-info/RECORD
