Metadata-Version: 2.1
Name: python-pytm
Version: 0.0.15
Summary: PyTM - an Open Source Python Time Management Tool for Mankind
Home-page: https://github.com/wasi0013/PyTM
Author: Wasi
Author-email: wasi0013@gmail.com
License: MIT
Keywords: PyTM
Classifier: Development Status :: 2 - Pre-Alpha
Classifier: Intended Audience :: Developers
Classifier: License :: OSI Approved :: MIT License
Classifier: Natural Language :: English
Classifier: Programming Language :: Python :: 3.12
License-File: LICENSE
License-File: AUTHORS.rst
Requires-Dist: click
Requires-Dist: rich
